jetblack_fixparser/__init__.py
jetblack_fixparser/py.typed
jetblack_fixparser/types.py
jetblack_fixparser/fix_message/__init__.py
jetblack_fixparser/fix_message/common.py
jetblack_fixparser/fix_message/decoder.py
jetblack_fixparser/fix_message/encoder.py
jetblack_fixparser/fix_message/errors.py
jetblack_fixparser/fix_message/fix_message.py
jetblack_fixparser/fix_message/fix_message_factory.py
jetblack_fixparser/fix_message/validation.py
jetblack_fixparser/fix_message/value_decoders.py
jetblack_fixparser/fix_message/value_encoders.py
jetblack_fixparser/loader/__init__.py
jetblack_fixparser/loader/fields.py
jetblack_fixparser/loader/loader.py
jetblack_fixparser/loader/messages.py
jetblack_fixparser/loader/quickfix_loader.py
jetblack_fixparser/loader/yaml_loader.py
jetblack_fixparser/meta_data/__init__.py
jetblack_fixparser/meta_data/message.py
jetblack_fixparser/meta_data/message_member.py
jetblack_fixparser/meta_data/protocol.py
jetblack_fixparser/meta_data/utils.py
jetblack_fixparser-2.5.0.dist-info/LICENSE
jetblack_fixparser-2.5.0.dist-info/METADATA
jetblack_fixparser-2.5.0.dist-info/WHEEL
jetblack_fixparser-2.5.0.dist-info/top_level.txt
jetblack_fixparser-2.5.0.dist-info/RECORD
