Metadata-Version: 2.1
Name: jetblack-fixparser
Version: 2.5.0
Summary: A parser for FIX messages
Author-email: Rob Blackbourn <rob.blackbourn@gmail.com>
Project-URL: Homepage, https://github.com/rob-blackbourn/jetblack-fixparser
Project-URL: Issues, https://github.com/rob-blackbourn/jetblack-fixparser/issues
Requires-Python: >=3.8
License-File: LICENSE
Requires-Dist: ruamel.yaml
